log_decorator/__init__.py
log_decorator/log_decorator.py
log_decorator-0.1.dist-info/LICENSE
log_decorator-0.1.dist-info/WHEEL
log_decorator-0.1.dist-info/METADATA
log_decorator-0.1.dist-info/RECORD
